ctss/Accuracy.py
ctss/Graphics.py
ctss/Statistica.py
ctss/__init__.py
ctss/blobs2roi.py
ctss/gt2blobs.py
ctss/jakkarAccuracy.py
CTSS-0.1.1.dist-info/LICENSE
CTSS-0.1.1.dist-info/METADATA
CTSS-0.1.1.dist-info/WHEEL
CTSS-0.1.1.dist-info/top_level.txt
CTSS-0.1.1.dist-info/RECORD
