Metadata-Version: 2.1
Name: CTSS
Version: 0.1.1
Summary: Software package for the CT&SS laboratory of Tula State University
Home-page: https://github.com/muwsik
Author: Mikhail Kurbakov
Author-email: muwa1997@mail.ru
License: UNKNOWN
Platform: UNKNOWN
Classifier: Programming Language :: Python :: 3
Classifier: License :: OSI Approved :: MIT License
Classifier: Operating System :: OS Independent
Requires-Python: >=3.*
License-File: LICENSE
Requires-Dist: numpy (>=1.21)
